odoo/addons/transfer_client_portfolio/README.rst
odoo/addons/transfer_client_portfolio/__init__.py
odoo/addons/transfer_client_portfolio/__manifest__.py
odoo/addons/transfer_client_portfolio/i18n/es.po
odoo/addons/transfer_client_portfolio/models/__init__.py
odoo/addons/transfer_client_portfolio/models/crm_lead.py
odoo/addons/transfer_client_portfolio/models/crm_stage.py
odoo/addons/transfer_client_portfolio/models/mail_activity.py
odoo/addons/transfer_client_portfolio/models/portfolio_transfer_registry.py
odoo/addons/transfer_client_portfolio/models/res_company.py
odoo/addons/transfer_client_portfolio/models/res_config_settings.py
odoo/addons/transfer_client_portfolio/models/res_partner.py
odoo/addons/transfer_client_portfolio/readme/CONFIGURE.md
odoo/addons/transfer_client_portfolio/readme/CONTRIBUTORS.md
odoo/addons/transfer_client_portfolio/readme/DESCRIPTION.md
odoo/addons/transfer_client_portfolio/readme/USAGE.md
odoo/addons/transfer_client_portfolio/security/ir.model.access.csv
odoo/addons/transfer_client_portfolio/security/res_groups.xml
odoo/addons/transfer_client_portfolio/static/description/icon.png
odoo/addons/transfer_client_portfolio/static/description/index.html
odoo/addons/transfer_client_portfolio/tests/__init__.py
odoo/addons/transfer_client_portfolio/tests/test_transfer_client_portfolio.py
odoo/addons/transfer_client_portfolio/views/crm_lead_views.xml
odoo/addons/transfer_client_portfolio/views/crm_stage_views.xml
odoo/addons/transfer_client_portfolio/views/portfolio_transfer_registry_views.xml
odoo/addons/transfer_client_portfolio/views/res_config_settings_view.xml
odoo/addons/transfer_client_portfolio/views/res_partner_views.xml
odoo/addons/transfer_client_portfolio/wizard/__init__.py
odoo/addons/transfer_client_portfolio/wizard/transfer_portfolio_wizard.py
odoo/addons/transfer_client_portfolio/wizard/transfer_portfolio_wizard_views.xml
odoo_addon_transfer_client_portfolio-15.0.1.2.0.2.dist-info/METADATA
odoo_addon_transfer_client_portfolio-15.0.1.2.0.2.dist-info/WHEEL
odoo_addon_transfer_client_portfolio-15.0.1.2.0.2.dist-info/top_level.txt
odoo_addon_transfer_client_portfolio-15.0.1.2.0.2.dist-info/RECORD
