Metadata-Version: 2.1
Name: odoo-addon-transfer_client_portfolio
Version: 15.0.1.2.0.2
Requires-Python: >=3.8
Requires-Dist: odoo>=15.0a,<15.1dev
Summary: Transfer Client Portfolio Between Salespersons.
Home-page: https://github.com/sygel-technology/sy-crm
License: AGPL-3
Author: Sygel, Odoo Community Association (OCA)
Author-email: support@odoo-community.org
Classifier: Programming Language :: Python
Classifier: Framework :: Odoo
Classifier: Framework :: Odoo :: 15.0
Classifier: License :: OSI Approved :: GNU Affero General Public License v3
